{
    "Name": "Van30_A3",
    "Number_of_nodes": 30,
    "Vehicle_capacity": 30571,
    "Total_supply_at_depot": 127383.0,
    "Maximum_tour_limit": 37164,
    "Number_of_vehicles": 5,
    "Total_travel_time_epsilon": 157947.0,
    "Gamma": 0.1,
    "Shortest_distances": {
        "(0, 1)": 840,
        "(0, 2)": 1440,
        "(0, 3)": 2880,
        "(0, 4)": 3540,
        "(0, 5)": 3540,
        "(0, 6)": 3720,
        "(0, 7)": 4500,
        "(0, 8)": 5220,
        "(0, 9)": 1440,
        "(0, 10)": 2880,
        "(0, 11)": 1800,
        "(0, 12)": 3060,
        "(0, 13)": 2760,
        "(0, 14)": 4680,
        "(0, 15)": 2160,
        "(0, 16)": 4320,
        "(0, 17)": 3060,
        "(0, 18)": 3120,
        "(0, 19)": 4680,
        "(0, 20)": 2460,
        "(0, 21)": 1680,
        "(0, 22)": 2220,
        "(0, 23)": 2580,
        "(0, 24)": 4740,
        "(0, 25)": 3600,
        "(0, 26)": 2940,
        "(0, 27)": 2100,
        "(0, 28)": 4560,
        "(0, 29)": 2340,
        "(0, 31)": 0,
        "(1, 0)": 840,
        "(1, 2)": 809.0,
        "(1, 3)": 2280.0,
        "(1, 4)": 3135.0,
        "(1, 5)": 3081.0,
        "(1, 6)": 3137.0,
        "(1, 7)": 4091.0,
        "(1, 8)": 4923.0,
        "(1, 9)": 1031.0,
        "(1, 10)": 2375.0,
        "(1, 11)": 1282.0,
        "(1, 12)": 2582.0,
        "(1, 13)": 2262.0,
        "(1, 14)": 4134.0,
        "(1, 15)": 1651.0,
        "(1, 16)": 3788.0,
        "(1, 17)": 2616.0,
        "(1, 18)": 2654.0,
        "(1, 19)": 4377.0,
        "(1, 20)": 1956.0,
        "(1, 21)": 1176.0,
        "(1, 22)": 1700.0,
        "(1, 23)": 1941.0,
        "(1, 24)": 4311.0,
        "(1, 25)": 3047.0,
        "(1, 26)": 2388.0,
        "(1, 27)": 1597.0,
        "(1, 28)": 4169.0,
        "(1, 29)": 1747.0,
        "(1, 31)": 0,
        "(2, 0)": 1440,
        "(2, 1)": 806.0,
        "(2, 3)": 1970.0,
        "(2, 4)": 3638.0,
        "(2, 5)": 3584.0,
        "(2, 6)": 2827.0,
        "(2, 7)": 4594.0,
        "(2, 8)": 5011.0,
        "(2, 9)": 1304.0,
        "(2, 10)": 2065.0,
        "(2, 11)": 1604.0,
        "(2, 12)": 3085.0,
        "(2, 13)": 2765.0,
        "(2, 14)": 3508.0,
        "(2, 15)": 1341.0,
        "(2, 16)": 3478.0,
        "(2, 17)": 3119.0,
        "(2, 18)": 3157.0,
        "(2, 19)": 4880.0,
        "(2, 20)": 1646.0,
        "(2, 21)": 1085.0,
        "(2, 22)": 2203.0,
        "(2, 23)": 1164.0,
        "(2, 24)": 4814.0,
        "(2, 25)": 2737.0,
        "(2, 26)": 2892.0,
        "(2, 27)": 1287.0,
        "(2, 28)": 4672.0,
        "(2, 29)": 1437.0,
        "(2, 31)": 0,
        "(3, 0)": 2880,
        "(3, 1)": 2316.0,
        "(3, 2)": 2071.0,
        "(3, 4)": 3583.0,
        "(3, 5)": 4663.0,
        "(3, 6)": 926.0,
        "(3, 7)": 4540.0,
        "(3, 8)": 3041.0,
        "(3, 9)": 3115.0,
        "(3, 10)": 530.0,
        "(3, 11)": 1933.0,
        "(3, 12)": 4164.0,
        "(3, 13)": 3844.0,
        "(3, 14)": 1923.0,
        "(3, 15)": 1229.0,
        "(3, 16)": 1791.0,
        "(3, 17)": 4198.0,
        "(3, 18)": 4236.0,
        "(3, 19)": 3587.0,
        "(3, 20)": 726.0,
        "(3, 21)": 3106.0,
        "(3, 22)": 3281.0,
        "(3, 23)": 1793.0,
        "(3, 24)": 3850.0,
        "(3, 25)": 836.0,
        "(3, 26)": 3970.0,
        "(3, 27)": 1616.0,
        "(3, 28)": 4501.0,
        "(3, 29)": 1393.0,
        "(3, 31)": 0,
        "(4, 0)": 3540,
        "(4, 1)": 3011.0,
        "(4, 2)": 3479.0,
        "(4, 3)": 3613.0,
        "(4, 5)": 2260.0,
        "(4, 6)": 4482.0,
        "(4, 7)": 957.0,
        "(4, 8)": 3755.0,
        "(4, 9)": 3809.0,
        "(4, 10)": 3721.0,
        "(4, 11)": 2889.0,
        "(4, 12)": 1761.0,
        "(4, 13)": 2773.0,
        "(4, 14)": 5479.0,
        "(4, 15)": 2993.0,
        "(4, 16)": 2104.0,
        "(4, 17)": 1218.0,
        "(4, 18)": 1833.0,
        "(4, 19)": 3209.0,
        "(4, 20)": 3302.0,
        "(4, 21)": 4040.0,
        "(4, 22)": 2192.0,
        "(4, 23)": 4119.0,
        "(4, 24)": 3143.0,
        "(4, 25)": 4393.0,
        "(4, 26)": 2881.0,
        "(4, 27)": 3190.0,
        "(4, 28)": 3001.0,
        "(4, 29)": 2946.0,
        "(4, 31)": 0,
        "(5, 0)": 3540,
        "(5, 1)": 3017.0,
        "(5, 2)": 3485.0,
        "(5, 3)": 4549.0,
        "(5, 4)": 2301.0,
        "(5, 6)": 5405.0,
        "(5, 7)": 3246.0,
        "(5, 8)": 3965.0,
        "(5, 9)": 3815.0,
        "(5, 10)": 4644.0,
        "(5, 11)": 2895.0,
        "(5, 12)": 489.0,
        "(5, 13)": 1217.0,
        "(5, 14)": 6403.0,
        "(5, 15)": 3920.0,
        "(5, 16)": 4043.0,
        "(5, 17)": 2043.0,
        "(5, 18)": 1137.0,
        "(5, 19)": 3420.0,
        "(5, 20)": 4225.0,
        "(5, 21)": 4046.0,
        "(5, 22)": 2068.0,
        "(5, 23)": 4616.0,
        "(5, 24)": 3353.0,
        "(5, 25)": 5316.0,
        "(5, 26)": 1531.0,
        "(5, 27)": 3201.0,
        "(5, 28)": 3211.0,
        "(5, 29)": 4016.0,
        "(5, 31)": 0,
        "(6, 0)": 3720,
        "(6, 1)": 3161.0,
        "(6, 2)": 2916.0,
        "(6, 3)": 958.0,
        "(6, 4)": 4515.0,
        "(6, 5)": 5507.0,
        "(6, 7)": 5472.0,
        "(6, 8)": 3999.0,
        "(6, 9)": 3960.0,
        "(6, 10)": 1374.0,
        "(6, 11)": 2778.0,
        "(6, 12)": 5008.0,
        "(6, 13)": 4689.0,
        "(6, 14)": 1946.0,
        "(6, 15)": 2073.0,
        "(6, 16)": 2749.0,
        "(6, 17)": 5042.0,
        "(6, 18)": 5080.0,
        "(6, 19)": 4545.0,
        "(6, 20)": 1571.0,
        "(6, 21)": 3950.0,
        "(6, 22)": 4126.0,
        "(6, 23)": 2638.0,
        "(6, 24)": 4808.0,
        "(6, 25)": 602.0,
        "(6, 26)": 4815.0,
        "(6, 27)": 2461.0,
        "(6, 28)": 5459.0,
        "(6, 29)": 2237.0,
        "(6, 31)": 0,
        "(7, 0)": 4500,
        "(7, 1)": 3944.0,
        "(7, 2)": 4412.0,
        "(7, 3)": 4566.0,
        "(7, 4)": 953.0,
        "(7, 5)": 3193.0,
        "(7, 6)": 5435.0,
        "(7, 8)": 4688.0,
        "(7, 9)": 4743.0,
        "(7, 10)": 4673.0,
        "(7, 11)": 3822.0,
        "(7, 12)": 2694.0,
        "(7, 13)": 3707.0,
        "(7, 14)": 6432.0,
        "(7, 15)": 3945.0,
        "(7, 16)": 3057.0,
        "(7, 17)": 2170.0,
        "(7, 18)": 2766.0,
        "(7, 19)": 4143.0,
        "(7, 20)": 4254.0,
        "(7, 21)": 4973.0,
        "(7, 22)": 3125.0,
        "(7, 23)": 5071.0,
        "(7, 24)": 4077.0,
        "(7, 25)": 5345.0,
        "(7, 26)": 3814.0,
        "(7, 27)": 4128.0,
        "(7, 28)": 3934.0,
        "(7, 29)": 3898.0,
        "(7, 31)": 0,
        "(8, 0)": 5220,
        "(8, 1)": 4672.0,
        "(8, 2)": 5137.0,
        "(8, 3)": 3066.0,
        "(8, 4)": 3594.0,
        "(8, 5)": 3921.0,
        "(8, 6)": 3992.0,
        "(8, 7)": 4539.0,
        "(8, 9)": 5470.0,
        "(8, 10)": 3596.0,
        "(8, 11)": 4550.0,
        "(8, 12)": 3422.0,
        "(8, 13)": 4434.0,
        "(8, 14)": 4990.0,
        "(8, 15)": 4295.0,
        "(8, 16)": 3038.0,
        "(8, 17)": 3409.0,
        "(8, 18)": 3494.0,
        "(8, 19)": 545.0,
        "(8, 20)": 3793.0,
        "(8, 21)": 5701.0,
        "(8, 22)": 3853.0,
        "(8, 23)": 4860.0,
        "(8, 24)": 1640.0,
        "(8, 25)": 3903.0,
        "(8, 26)": 4542.0,
        "(8, 27)": 4682.0,
        "(8, 28)": 1498.0,
        "(8, 29)": 4459.0,
        "(8, 31)": 0,
        "(9, 0)": 1440,
        "(9, 1)": 972.0,
        "(9, 2)": 1340.0,
        "(9, 3)": 3142.0,
        "(9, 4)": 3895.0,
        "(9, 5)": 3841.0,
        "(9, 6)": 3999.0,
        "(9, 7)": 4852.0,
        "(9, 8)": 5683.0,
        "(9, 10)": 3237.0,
        "(9, 11)": 2143.0,
        "(9, 12)": 3342.0,
        "(9, 13)": 3023.0,
        "(9, 14)": 4816.0,
        "(9, 15)": 2513.0,
        "(9, 16)": 4650.0,
        "(9, 17)": 3376.0,
        "(9, 18)": 3414.0,
        "(9, 19)": 5138.0,
        "(9, 20)": 2818.0,
        "(9, 21)": 1535.0,
        "(9, 22)": 2460.0,
        "(9, 23)": 2471.0,
        "(9, 24)": 5072.0,
        "(9, 25)": 3909.0,
        "(9, 26)": 3149.0,
        "(9, 27)": 2459.0,
        "(9, 28)": 4929.0,
        "(9, 29)": 2609.0,
        "(9, 31)": 0,
        "(10, 0)": 2880,
        "(10, 1)": 2370.0,
        "(10, 2)": 2124.0,
        "(10, 3)": 527.0,
        "(10, 4)": 3724.0,
        "(10, 5)": 4716.0,
        "(10, 6)": 1383.0,
        "(10, 7)": 4680.0,
        "(10, 8)": 3568.0,
        "(10, 9)": 3168.0,
        "(10, 11)": 1986.0,
        "(10, 12)": 4217.0,
        "(10, 13)": 3898.0,
        "(10, 14)": 2381.0,
        "(10, 15)": 1282.0,
        "(10, 16)": 2317.0,
        "(10, 17)": 4251.0,
        "(10, 18)": 4289.0,
        "(10, 19)": 4113.0,
        "(10, 20)": 780.0,
        "(10, 21)": 3159.0,
        "(10, 22)": 3335.0,
        "(10, 23)": 1847.0,
        "(10, 24)": 4377.0,
        "(10, 25)": 1294.0,
        "(10, 26)": 4024.0,
        "(10, 27)": 1669.0,
        "(10, 28)": 5028.0,
        "(10, 29)": 1446.0,
        "(10, 31)": 0,
        "(11, 0)": 1800,
        "(11, 1)": 1271.0,
        "(11, 2)": 1701.0,
        "(11, 3)": 1876.0,
        "(11, 4)": 3021.0,
        "(11, 5)": 2967.0,
        "(11, 6)": 2733.0,
        "(11, 7)": 3977.0,
        "(11, 8)": 4809.0,
        "(11, 9)": 2069.0,
        "(11, 10)": 1971.0,
        "(11, 12)": 2468.0,
        "(11, 13)": 2301.0,
        "(11, 14)": 3730.0,
        "(11, 15)": 1243.0,
        "(11, 16)": 3232.0,
        "(11, 17)": 2502.0,
        "(11, 18)": 2540.0,
        "(11, 19)": 4263.0,
        "(11, 20)": 1552.0,
        "(11, 21)": 2300.0,
        "(11, 22)": 1739.0,
        "(11, 23)": 2369.0,
        "(11, 24)": 4197.0,
        "(11, 25)": 2643.0,
        "(11, 26)": 2428.0,
        "(11, 27)": 306.0,
        "(11, 28)": 4055.0,
        "(11, 29)": 1191.0,
        "(11, 31)": 0,
        "(12, 0)": 3060,
        "(12, 1)": 2528.0,
        "(12, 2)": 2996.0,
        "(12, 3)": 4060.0,
        "(12, 4)": 1812.0,
        "(12, 5)": 499.0,
        "(12, 6)": 4916.0,
        "(12, 7)": 2757.0,
        "(12, 8)": 3476.0,
        "(12, 9)": 3326.0,
        "(12, 10)": 4155.0,
        "(12, 11)": 2406.0,
        "(12, 13)": 1012.0,
        "(12, 14)": 5914.0,
        "(12, 15)": 3431.0,
        "(12, 16)": 3554.0,
        "(12, 17)": 1554.0,
        "(12, 18)": 648.0,
        "(12, 19)": 2931.0,
        "(12, 20)": 3736.0,
        "(12, 21)": 3557.0,
        "(12, 22)": 1709.0,
        "(12, 23)": 4127.0,
        "(12, 24)": 2864.0,
        "(12, 25)": 4827.0,
        "(12, 26)": 1326.0,
        "(12, 27)": 2712.0,
        "(12, 28)": 2722.0,
        "(12, 29)": 3527.0,
        "(12, 31)": 0,
        "(13, 0)": 2760,
        "(13, 1)": 2245.0,
        "(13, 2)": 2713.0,
        "(13, 3)": 3777.0,
        "(13, 4)": 2716.0,
        "(13, 5)": 1212.0,
        "(13, 6)": 4634.0,
        "(13, 7)": 3673.0,
        "(13, 8)": 4505.0,
        "(13, 9)": 3044.0,
        "(13, 10)": 3873.0,
        "(13, 11)": 2279.0,
        "(13, 12)": 1029.0,
        "(13, 14)": 5631.0,
        "(13, 15)": 3149.0,
        "(13, 16)": 4331.0,
        "(13, 17)": 2198.0,
        "(13, 18)": 1677.0,
        "(13, 19)": 3960.0,
        "(13, 20)": 3454.0,
        "(13, 21)": 3275.0,
        "(13, 22)": 851.0,
        "(13, 23)": 3845.0,
        "(13, 24)": 3894.0,
        "(13, 25)": 4545.0,
        "(13, 26)": 313.0,
        "(13, 27)": 2585.0,
        "(13, 28)": 3751.0,
        "(13, 29)": 3245.0,
        "(13, 31)": 0,
        "(14, 0)": 4680,
        "(14, 1)": 4128.0,
        "(14, 2)": 3530.0,
        "(14, 3)": 1925.0,
        "(14, 4)": 5482.0,
        "(14, 5)": 6475.0,
        "(14, 6)": 1954.0,
        "(14, 7)": 6439.0,
        "(14, 8)": 4967.0,
        "(14, 9)": 4775.0,
        "(14, 10)": 2342.0,
        "(14, 11)": 3745.0,
        "(14, 12)": 5976.0,
        "(14, 13)": 5656.0,
        "(14, 15)": 3041.0,
        "(14, 16)": 3716.0,
        "(14, 17)": 6010.0,
        "(14, 18)": 6048.0,
        "(14, 19)": 5512.0,
        "(14, 20)": 2538.0,
        "(14, 21)": 4518.0,
        "(14, 22)": 5094.0,
        "(14, 23)": 2742.0,
        "(14, 24)": 5775.0,
        "(14, 25)": 1344.0,
        "(14, 26)": 5782.0,
        "(14, 27)": 3428.0,
        "(14, 28)": 6427.0,
        "(14, 29)": 3205.0,
        "(14, 31)": 0,
        "(15, 0)": 2160,
        "(15, 1)": 1643.0,
        "(15, 2)": 1397.0,
        "(15, 3)": 1229.0,
        "(15, 4)": 2996.0,
        "(15, 5)": 3989.0,
        "(15, 6)": 2085.0,
        "(15, 7)": 3952.0,
        "(15, 8)": 4270.0,
        "(15, 9)": 2441.0,
        "(15, 10)": 1324.0,
        "(15, 11)": 1258.0,
        "(15, 12)": 3490.0,
        "(15, 13)": 3171.0,
        "(15, 14)": 3083.0,
        "(15, 16)": 2759.0,
        "(15, 17)": 3524.0,
        "(15, 18)": 3562.0,
        "(15, 19)": 4815.0,
        "(15, 20)": 905.0,
        "(15, 21)": 2432.0,
        "(15, 22)": 2608.0,
        "(15, 23)": 1722.0,
        "(15, 24)": 5079.0,
        "(15, 25)": 1996.0,
        "(15, 26)": 3297.0,
        "(15, 27)": 941.0,
        "(15, 28)": 5077.0,
        "(15, 29)": 718.0,
        "(15, 31)": 0,
        "(16, 0)": 4320,
        "(16, 1)": 3798.0,
        "(16, 2)": 3552.0,
        "(16, 3)": 1809.0,
        "(16, 4)": 2102.0,
        "(16, 5)": 3931.0,
        "(16, 6)": 2735.0,
        "(16, 7)": 3059.0,
        "(16, 8)": 3001.0,
        "(16, 9)": 4596.0,
        "(16, 10)": 2338.0,
        "(16, 11)": 3248.0,
        "(16, 12)": 3432.0,
        "(16, 13)": 4388.0,
        "(16, 14)": 3732.0,
        "(16, 15)": 2734.0,
        "(16, 17)": 2809.0,
        "(16, 18)": 3504.0,
        "(16, 19)": 3084.0,
        "(16, 20)": 2535.0,
        "(16, 21)": 4587.0,
        "(16, 22)": 3825.0,
        "(16, 23)": 3602.0,
        "(16, 24)": 3156.0,
        "(16, 25)": 2645.0,
        "(16, 26)": 4514.0,
        "(16, 27)": 2931.0,
        "(16, 28)": 3013.0,
        "(16, 29)": 2687.0,
        "(16, 31)": 0,
        "(17, 0)": 3060,
        "(17, 1)": 2508.0,
        "(17, 2)": 2976.0,
        "(17, 3)": 4040.0,
        "(17, 4)": 1225.0,
        "(17, 5)": 2044.0,
        "(17, 6)": 4896.0,
        "(17, 7)": 2181.0,
        "(17, 8)": 3548.0,
        "(17, 9)": 3306.0,
        "(17, 10)": 4135.0,
        "(17, 11)": 2386.0,
        "(17, 12)": 1545.0,
        "(17, 13)": 2252.0,
        "(17, 14)": 5894.0,
        "(17, 15)": 3411.0,
        "(17, 16)": 2839.0,
        "(17, 18)": 1617.0,
        "(17, 19)": 3003.0,
        "(17, 20)": 3716.0,
        "(17, 21)": 3537.0,
        "(17, 22)": 1689.0,
        "(17, 23)": 4107.0,
        "(17, 24)": 2936.0,
        "(17, 25)": 4807.0,
        "(17, 26)": 2378.0,
        "(17, 27)": 2692.0,
        "(17, 28)": 2794.0,
        "(17, 29)": 3507.0,
        "(17, 31)": 0,
        "(18, 0)": 3120,
        "(18, 1)": 2591.0,
        "(18, 2)": 3059.0,
        "(18, 3)": 4123.0,
        "(18, 4)": 1875.0,
        "(18, 5)": 1159.0,
        "(18, 6)": 4979.0,
        "(18, 7)": 2820.0,
        "(18, 8)": 3539.0,
        "(18, 9)": 3389.0,
        "(18, 10)": 4218.0,
        "(18, 11)": 2469.0,
        "(18, 12)": 660.0,
        "(18, 13)": 1672.0,
        "(18, 14)": 5977.0,
        "(18, 15)": 3494.0,
        "(18, 16)": 3617.0,
        "(18, 17)": 1617.0,
        "(18, 19)": 2994.0,
        "(18, 20)": 3799.0,
        "(18, 21)": 3620.0,
        "(18, 22)": 1772.0,
        "(18, 23)": 4190.0,
        "(18, 24)": 2927.0,
        "(18, 25)": 4890.0,
        "(18, 26)": 1986.0,
        "(18, 27)": 2775.0,
        "(18, 28)": 2785.0,
        "(18, 29)": 3590.0,
        "(18, 31)": 0,
        "(19, 0)": 4680,
        "(19, 1)": 4126.0,
        "(19, 2)": 4594.0,
        "(19, 3)": 3612.0,
        "(19, 4)": 3048.0,
        "(19, 5)": 3376.0,
        "(19, 6)": 4538.0,
        "(19, 7)": 3994.0,
        "(19, 8)": 545.0,
        "(19, 9)": 4925.0,
        "(19, 10)": 4141.0,
        "(19, 11)": 4004.0,
        "(19, 12)": 2877.0,
        "(19, 13)": 3889.0,
        "(19, 14)": 5535.0,
        "(19, 15)": 4840.0,
        "(19, 16)": 3048.0,
        "(19, 17)": 2864.0,
        "(19, 18)": 2949.0,
        "(19, 20)": 4338.0,
        "(19, 21)": 5156.0,
        "(19, 22)": 3308.0,
        "(19, 23)": 5405.0,
        "(19, 24)": 1095.0,
        "(19, 25)": 4448.0,
        "(19, 26)": 3996.0,
        "(19, 27)": 4310.0,
        "(19, 28)": 953.0,
        "(19, 29)": 5004.0,
        "(19, 31)": 0,
        "(20, 0)": 2460,
        "(20, 1)": 1951.0,
        "(20, 2)": 1705.0,
        "(20, 3)": 723.0,
        "(20, 4)": 3305.0,
        "(20, 5)": 4297.0,
        "(20, 6)": 1580.0,
        "(20, 7)": 4261.0,
        "(20, 8)": 3765.0,
        "(20, 9)": 2749.0,
        "(20, 10)": 819.0,
        "(20, 11)": 1567.0,
        "(20, 12)": 3798.0,
        "(20, 13)": 3479.0,
        "(20, 14)": 2577.0,
        "(20, 15)": 863.0,
        "(20, 16)": 2514.0,
        "(20, 17)": 3832.0,
        "(20, 18)": 3870.0,
        "(20, 19)": 4310.0,
        "(20, 21)": 2843.0,
        "(20, 22)": 2916.0,
        "(20, 23)": 1067.0,
        "(20, 24)": 4573.0,
        "(20, 25)": 1491.0,
        "(20, 26)": 3605.0,
        "(20, 27)": 1250.0,
        "(20, 28)": 5225.0,
        "(20, 29)": 1027.0,
        "(20, 31)": 0,
        "(21, 0)": 1680,
        "(21, 1)": 1188.0,
        "(21, 2)": 1137.0,
        "(21, 3)": 3107.0,
        "(21, 4)": 4111.0,
        "(21, 5)": 4057.0,
        "(21, 6)": 3963.0,
        "(21, 7)": 5067.0,
        "(21, 8)": 5899.0,
        "(21, 9)": 1508.0,
        "(21, 10)": 3202.0,
        "(21, 11)": 2213.0,
        "(21, 12)": 3558.0,
        "(21, 13)": 3239.0,
        "(21, 14)": 4539.0,
        "(21, 15)": 2478.0,
        "(21, 16)": 4615.0,
        "(21, 17)": 3592.0,
        "(21, 18)": 3630.0,
        "(21, 19)": 5354.0,
        "(21, 20)": 2783.0,
        "(21, 22)": 2676.0,
        "(21, 23)": 2195.0,
        "(21, 24)": 5287.0,
        "(21, 25)": 3874.0,
        "(21, 26)": 3365.0,
        "(21, 27)": 2424.0,
        "(21, 28)": 5145.0,
        "(21, 29)": 2574.0,
        "(21, 31)": 0,
        "(22, 0)": 2220,
        "(22, 1)": 1700.0,
        "(22, 2)": 2168.0,
        "(22, 3)": 3231.0,
        "(22, 4)": 2171.0,
        "(22, 5)": 2054.0,
        "(22, 6)": 4088.0,
        "(22, 7)": 3127.0,
        "(22, 8)": 3959.0,
        "(22, 9)": 2498.0,
        "(22, 10)": 3327.0,
        "(22, 11)": 1734.0,
        "(22, 12)": 1618.0,
        "(22, 13)": 842.0,
        "(22, 14)": 5086.0,
        "(22, 15)": 2603.0,
        "(22, 16)": 3785.0,
        "(22, 17)": 1652.0,
        "(22, 18)": 1690.0,
        "(22, 19)": 3414.0,
        "(22, 20)": 2908.0,
        "(22, 21)": 2729.0,
        "(22, 23)": 3299.0,
        "(22, 24)": 3347.0,
        "(22, 25)": 3999.0,
        "(22, 26)": 968.0,
        "(22, 27)": 2040.0,
        "(22, 28)": 3205.0,
        "(22, 29)": 2699.0,
        "(22, 31)": 0,
        "(23, 0)": 2580,
        "(23, 1)": 1924.0,
        "(23, 2)": 1177.0,
        "(23, 3)": 1796.0,
        "(23, 4)": 4117.0,
        "(23, 5)": 4701.0,
        "(23, 6)": 2653.0,
        "(23, 7)": 5073.0,
        "(23, 8)": 4838.0,
        "(23, 9)": 2421.0,
        "(23, 10)": 1892.0,
        "(23, 11)": 2379.0,
        "(23, 12)": 4202.0,
        "(23, 13)": 3883.0,
        "(23, 14)": 2748.0,
        "(23, 15)": 1675.0,
        "(23, 16)": 3587.0,
        "(23, 17)": 4236.0,
        "(23, 18)": 4274.0,
        "(23, 19)": 5383.0,
        "(23, 20)": 1073.0,
        "(23, 21)": 2165.0,
        "(23, 22)": 3320.0,
        "(23, 24)": 5646.0,
        "(23, 25)": 2564.0,
        "(23, 26)": 4009.0,
        "(23, 27)": 2062.0,
        "(23, 28)": 5789.0,
        "(23, 29)": 1839.0,
        "(23, 31)": 0,
        "(24, 0)": 4740,
        "(24, 1)": 4209.0,
        "(24, 2)": 4677.0,
        "(24, 3)": 3861.0,
        "(24, 4)": 3131.0,
        "(24, 5)": 3458.0,
        "(24, 6)": 4787.0,
        "(24, 7)": 4077.0,
        "(24, 8)": 1642.0,
        "(24, 9)": 5008.0,
        "(24, 10)": 4391.0,
        "(24, 11)": 4087.0,
        "(24, 12)": 2959.0,
        "(24, 13)": 3972.0,
        "(24, 14)": 5784.0,
        "(24, 15)": 5090.0,
        "(24, 16)": 3290.0,
        "(24, 17)": 2946.0,
        "(24, 18)": 3031.0,
        "(24, 19)": 1097.0,
        "(24, 20)": 4587.0,
        "(24, 21)": 5238.0,
        "(24, 22)": 3390.0,
        "(24, 23)": 5654.0,
        "(24, 25)": 4697.0,
        "(24, 26)": 4079.0,
        "(24, 27)": 4393.0,
        "(24, 28)": 651.0,
        "(24, 29)": 5208.0,
        "(24, 31)": 0,
        "(25, 0)": 3600,
        "(25, 1)": 3041.0,
        "(25, 2)": 2795.0,
        "(25, 3)": 837.0,
        "(25, 4)": 4395.0,
        "(25, 5)": 5387.0,
        "(25, 6)": 610.0,
        "(25, 7)": 5351.0,
        "(25, 8)": 3879.0,
        "(25, 9)": 3839.0,
        "(25, 10)": 1254.0,
        "(25, 11)": 2657.0,
        "(25, 12)": 4888.0,
        "(25, 13)": 4569.0,
        "(25, 14)": 1344.0,
        "(25, 15)": 1953.0,
        "(25, 16)": 2628.0,
        "(25, 17)": 4922.0,
        "(25, 18)": 4960.0,
        "(25, 19)": 4424.0,
        "(25, 20)": 1451.0,
        "(25, 21)": 3830.0,
        "(25, 22)": 4006.0,
        "(25, 23)": 2518.0,
        "(25, 24)": 4687.0,
        "(25, 26)": 4695.0,
        "(25, 27)": 2340.0,
        "(25, 28)": 5339.0,
        "(25, 29)": 2117.0,
        "(25, 31)": 0,
        "(26, 0)": 2940,
        "(26, 1)": 2381.0,
        "(26, 2)": 2850.0,
        "(26, 3)": 3913.0,
        "(26, 4)": 2853.0,
        "(26, 5)": 1521.0,
        "(26, 6)": 4770.0,
        "(26, 7)": 3809.0,
        "(26, 8)": 4641.0,
        "(26, 9)": 3180.0,
        "(26, 10)": 4009.0,
        "(26, 11)": 2416.0,
        "(26, 12)": 1338.0,
        "(26, 13)": 308.0,
        "(26, 14)": 5767.0,
        "(26, 15)": 3285.0,
        "(26, 16)": 4467.0,
        "(26, 17)": 2334.0,
        "(26, 18)": 1986.0,
        "(26, 19)": 4095.0,
        "(26, 20)": 3590.0,
        "(26, 21)": 3411.0,
        "(26, 22)": 987.0,
        "(26, 23)": 3981.0,
        "(26, 24)": 4029.0,
        "(26, 25)": 4681.0,
        "(26, 27)": 2722.0,
        "(26, 28)": 3887.0,
        "(26, 29)": 3381.0,
        "(26, 31)": 0,
        "(27, 0)": 2100,
        "(27, 1)": 1534.0,
        "(27, 2)": 1395.0,
        "(27, 3)": 1570.0,
        "(27, 4)": 3163.0,
        "(27, 5)": 3284.0,
        "(27, 6)": 2427.0,
        "(27, 7)": 4120.0,
        "(27, 8)": 4611.0,
        "(27, 9)": 2332.0,
        "(27, 10)": 1665.0,
        "(27, 11)": 317.0,
        "(27, 12)": 2785.0,
        "(27, 13)": 2618.0,
        "(27, 14)": 3424.0,
        "(27, 15)": 937.0,
        "(27, 16)": 2926.0,
        "(27, 17)": 2819.0,
        "(27, 18)": 2857.0,
        "(27, 19)": 4580.0,
        "(27, 20)": 1246.0,
        "(27, 21)": 2430.0,
        "(27, 22)": 2056.0,
        "(27, 23)": 2063.0,
        "(27, 24)": 4514.0,
        "(27, 25)": 2337.0,
        "(27, 26)": 2745.0,
        "(27, 28)": 4372.0,
        "(27, 29)": 885.0,
        "(27, 31)": 0,
        "(28, 0)": 4560,
        "(28, 1)": 4023.0,
        "(28, 2)": 4491.0,
        "(28, 3)": 4376.0,
        "(28, 4)": 2945.0,
        "(28, 5)": 3272.0,
        "(28, 6)": 5302.0,
        "(28, 7)": 3890.0,
        "(28, 8)": 1456.0,
        "(28, 9)": 4821.0,
        "(28, 10)": 4906.0,
        "(28, 11)": 3901.0,
        "(28, 12)": 2773.0,
        "(28, 13)": 3785.0,
        "(28, 14)": 6300.0,
        "(28, 15)": 4926.0,
        "(28, 16)": 3103.0,
        "(28, 17)": 2760.0,
        "(28, 18)": 2845.0,
        "(28, 19)": 911.0,
        "(28, 20)": 5103.0,
        "(28, 21)": 5052.0,
        "(28, 22)": 3204.0,
        "(28, 23)": 5622.0,
        "(28, 24)": 515.0,
        "(28, 25)": 5213.0,
        "(28, 26)": 3893.0,
        "(28, 27)": 4207.0,
        "(28, 29)": 5022.0,
        "(28, 31)": 0,
        "(29, 0)": 2340,
        "(29, 1)": 1782.0,
        "(29, 2)": 1536.0,
        "(29, 3)": 1351.0,
        "(29, 4)": 2924.0,
        "(29, 5)": 4128.0,
        "(29, 6)": 2207.0,
        "(29, 7)": 3880.0,
        "(29, 8)": 4392.0,
        "(29, 9)": 2580.0,
        "(29, 10)": 1446.0,
        "(29, 11)": 1232.0,
        "(29, 12)": 3629.0,
        "(29, 13)": 3310.0,
        "(29, 14)": 3205.0,
        "(29, 15)": 718.0,
        "(29, 16)": 2687.0,
        "(29, 17)": 3631.0,
        "(29, 18)": 3701.0,
        "(29, 19)": 4937.0,
        "(29, 20)": 1027.0,
        "(29, 21)": 2571.0,
        "(29, 22)": 2747.0,
        "(29, 23)": 1844.0,
        "(29, 24)": 5201.0,
        "(29, 25)": 2118.0,
        "(29, 26)": 3436.0,
        "(29, 27)": 915.0,
        "(29, 28)": 5216.0,
        "(29, 31)": 0,
        "(31, 0)": 3420,
        "(31, 1)": 2881.0,
        "(31, 2)": 2636.0,
        "(31, 3)": 678.0,
        "(31, 4)": 4235.0,
        "(31, 5)": 5227.0,
        "(31, 6)": 729.0,
        "(31, 7)": 5192.0,
        "(31, 8)": 3719.0,
        "(31, 9)": 3680.0,
        "(31, 10)": 1094.0,
        "(31, 11)": 2498.0,
        "(31, 12)": 4728.0,
        "(31, 13)": 4409.0,
        "(31, 14)": 1247.0,
        "(31, 15)": 1793.0,
        "(31, 16)": 2469.0,
        "(31, 17)": 4762.0,
        "(31, 18)": 4800.0,
        "(31, 19)": 4265.0,
        "(31, 20)": 1291.0,
        "(31, 21)": 3670.0,
        "(31, 22)": 3846.0,
        "(31, 23)": 2358.0,
        "(31, 24)": 4528.0,
        "(31, 25)": 639.0,
        "(31, 26)": 4535.0,
        "(31, 27)": 2181.0,
        "(31, 28)": 5179.0,
        "(31, 29)": 1957.0
    },
    "Node_info": {
        "1": {
            "demand": 140051.1087396211,
            "coordinates": [
                0.0,
                0.0
            ]
        },
        "2": {
            "demand": 8682.346995774291,
            "coordinates": [
                -3013.09500000049,
                -4185.825000000527
            ]
        },
        "3": {
            "demand": 2683.8941844434253,
            "coordinates": [
                -4466.973000000422,
                -8783.900000000245
            ]
        },
        "4": {
            "demand": 492.1922817973898,
            "coordinates": [
                -20602.377000000502,
                -27183.4250000002
            ]
        },
        "5": {
            "demand": 1305.5844686831276,
            "coordinates": [
                -25169.2500000003,
                -36514.81000000004
            ]
        },
        "6": {
            "demand": 489.74450306385756,
            "coordinates": [
                -23112.974999999864,
                7554.629999999492
            ]
        },
        "7": {
            "demand": 2220.602769938059,
            "coordinates": [
                2010.5429999999558,
                -11074.734999999975
            ]
        },
        "8": {
            "demand": 810.9290527195976,
            "coordinates": [
                -11397.258000000498,
                5720.414999999868
            ]
        },
        "9": {
            "demand": 701.8688643696116,
            "coordinates": [
                -19690.845000000463,
                -37243.43000000012
            ]
        },
        "10": {
            "demand": 1377.3986296670537,
            "coordinates": [
                -14737.35900000036,
                9674.019999999644
            ]
        },
        "11": {
            "demand": 1478.4523331300616,
            "coordinates": [
                -5510.594999999796,
                -15604.725000000066
            ]
        },
        "12": {
            "demand": 1695.1274986766985,
            "coordinates": [
                -44204.52900000042,
                -15028.935000000061
            ]
        },
        "13": {
            "demand": 1116.0804030716295,
            "coordinates": [
                -40795.27500000006,
                -9057.515000000365
            ]
        },
        "14": {
            "demand": 457.99725576353353,
            "coordinates": [
                -13333.764000000458,
                -11117.915000000274
            ]
        },
        "15": {
            "demand": 1651.5044459379583,
            "coordinates": [
                -7537.899000000024,
                -24502.270000000266
            ]
        },
        "16": {
            "demand": 2316.385672993729,
            "coordinates": [
                -24065.022000000143,
                -1188.5550000002709
            ]
        },
        "17": {
            "demand": 1383.9436279478311,
            "coordinates": [
                -30257.49000000011,
                1387.9649999999087
            ]
        },
        "18": {
            "demand": 480.2243901321419,
            "coordinates": [
                -40565.17200000053,
                1300.4149999999015
            ]
        },
        "19": {
            "demand": 1232.150366562299,
            "coordinates": [
                -31390.68900000047,
                -24144.845000000358
            ]
        },
        "20": {
            "demand": 917.8975189361804,
            "coordinates": [
                -8584.851000000455,
                -554.455000000118
            ]
        },
        "21": {
            "demand": 1836.104430457413,
            "coordinates": [
                -13251.84599999985,
                -37261.70500000048
            ]
        },
        "22": {
            "demand": 1963.2683144345267,
            "coordinates": [
                -4787.541000000275,
                -10491.039999999997
            ]
        },
        "23": {
            "demand": 978.0928122143248,
            "coordinates": [
                -24407.124000000047,
                -7170.090000000399
            ]
        },
        "24": {
            "demand": 374.4251792512313,
            "coordinates": [
                -902.5409999998644,
                -9935.990000000174
            ]
        },
        "25": {
            "demand": 1022.5398522232266,
            "coordinates": [
                -7426.121999999878,
                -11088.675000000414
            ]
        },
        "26": {
            "demand": 1827.7774978414186,
            "coordinates": [
                1436.007000000096,
                -6613.425000000426
            ]
        },
        "27": {
            "demand": 776.2931656386986,
            "coordinates": [
                -29603.5890000003,
                -7089.510000000309
            ]
        },
        "28": {
            "demand": 1190.3021058263316,
            "coordinates": [
                -9441.771000000352,
                -31276.260000000562
            ]
        },
        "29": {
            "demand": 441.04121965014497,
            "coordinates": [
                -32917.38300000033,
                -6287.0250000001
            ]
        },
        "0": {
            "demand": 0,
            "coordinates": [
                -33452.292000000074,
                -20892.830000000053
            ]
        },
        "31": {
            "demand": 0,
            "coordinates": [
                -33452.292000000074,
                -20892.830000000053
            ]
        }
    }
}